{
	"React map": {
    "prefix": "rmap",
		"body": [
			"{${1:arr}.map((${2:el}, index) => {",
			"\treturn <${3:El} key={`${1:arr}-${index}`}>${4:content}</${3:El}>",
			"})}"
		],
		"description": "Component map loop"
	},
	"React import component absolute": {
    "prefix": "rimpa",
		"body": [
			"import ${1:Component} from '@/$2${1:Component}'"
		],
		"description": "React import component absolutely"
	},
  "React import component relative": {
    "prefix": "rimpr",
		"body": [
			"import ${1:Component} from '${2:.}/$3${1:Component}'"
		],
		"description": "React import component relatively"
	},
	"Class name Array": {
		"prefix": "cna",
		"body": "className={[$1].join(' ')}",
		"description": "Create an empty array of classname"
	},
	"Dangerously set HTML": {
		"prefix": "danger",
		"body": "dangerouslySetInnerHTML={{ __html: ${1:html} }}",
		"description": "dangerouslySetInnerHTML prop"
	}
}